coinapi/__init__.py
coinapi/base.py
coinapi/config.py
coinapi/exchange_rates.py
coinapi/indexes.py
coinapi/metadata.py
coinapi/metrics.py
coinapi/ohlcv.py
coinapi/order_book.py
coinapi/order_book_l3.py
coinapi/py.typed
coinapi/quotes.py
coinapi/rest.py
coinapi/trades.py
coinapi/_hooks/__init__.py
coinapi/_hooks/hook_types.py
coinapi/_hooks/hooks.py
coinapi/models/__init__.py
coinapi/models/components/__init__.py
coinapi/models/components/model_vwap24refrate.py
coinapi/models/components/models_exchangetimeseriesitem.py
coinapi/models/components/security.py
coinapi/models/components/v1_asset.py
coinapi/models/components/v1_exchange.py
coinapi/models/components/v1_exchangerate.py
coinapi/models/components/v1_exchangeratesrate.py
coinapi/models/components/v1_exchangeratestimeseriesitem.py
coinapi/models/components/v1_generaldata.py
coinapi/models/components/v1_icon.py
coinapi/models/components/v1_index.py
coinapi/models/components/v1_indexdata.py
coinapi/models/components/v1_indexdatacomponent.py
coinapi/models/components/v1_indexdataresponse.py
coinapi/models/components/v1_indextimeseriesitem.py
coinapi/models/components/v1_indexvalue.py
coinapi/models/components/v1_indexvaluecomponent.py
coinapi/models/components/v1_lasttrade.py
coinapi/models/components/v1_listingitem.py
coinapi/models/components/v1_metric.py
coinapi/models/components/v1_metricdata.py
coinapi/models/components/v1_orderbook.py
coinapi/models/components/v1_orderbookbase.py
coinapi/models/components/v1_orderbookdepth.py
coinapi/models/components/v1_quote.py
coinapi/models/components/v1_quotetrade.py
coinapi/models/components/v1_symbol.py
coinapi/models/components/v1_symbolmapping.py
coinapi/models/components/v1_timeseriesitem.py
coinapi/models/components/v1_timeseriesperiod.py
coinapi/models/components/v1_trade.py
coinapi/models/errors/__init__.py
coinapi/models/errors/coinapierror.py
coinapi/models/operations/__init__.py
coinapi/models/operations/base.py
coinapi/models/operations/get_v1_assets.py
coinapi_rest-0.0.6.dist-info/METADATA
coinapi_rest-0.0.6.dist-info/WHEEL
coinapi_rest-0.0.6.dist-info/RECORD
