Metadata-Version: 2.4
Name: coinapi-rest
Version: 0.0.6
Summary: CoinAPI Python REST Client
Project-URL: repository, https://github.com/ljnsn/coinapi-rest
Author-email: ljnsn <info@ljnsn.com>
License-Expression: MIT
Keywords: coinapi,crypto,cryptocurrency,prices
Classifier: Development Status :: 4 - Beta
Classifier: Intended Audience :: Developers
Classifier: License :: OSI Approved :: MIT License
Classifier: Operating System :: OS Independent
Classifier: Programming Language :: Python
Classifier: Programming Language :: Python :: 3 :: Only
Classifier: Programming Language :: Python :: 3.10
Classifier: Programming Language :: Python :: 3.11
Classifier: Programming Language :: Python :: 3.12
Classifier: Programming Language :: Python :: 3.13
Classifier: Topic :: Software Development :: Libraries
Classifier: Topic :: Software Development :: Libraries :: Python Modules
Classifier: Typing :: Typed
Requires-Python: >=3.10
Requires-Dist: httpx>=0.27.0
Requires-Dist: msgspec>=0.18.6
Requires-Dist: python-dotenv>=1.0.1
Requires-Dist: typing-inspect>=0.9.0
